django_datacite/__init__.py
django_datacite/admin.py
django_datacite/apps.py
django_datacite/exports.py
django_datacite/imports.py
django_datacite/models.py
django_datacite/renderers.py
django_datacite/settings.py
django_datacite/urls.py
django_datacite/utils.py
django_datacite/validators.py
django_datacite/views.py
django_datacite/migrations/0001_initial.py
django_datacite/migrations/0002_alter_resource_identifier.py
django_datacite/migrations/0003_add_geo_location.py
django_datacite/migrations/0004_add_funding_reference.py
django_datacite/migrations/0005_add_related_item.py
django_datacite/migrations/0006_resource_public.py
django_datacite/migrations/0007_use_integer_field_for_order.py
django_datacite/migrations/0008_change_ordering.py
django_datacite/migrations/0009_change_ordering.py
django_datacite/migrations/0010_subjects_m2m.py
django_datacite/migrations/0011_alter_subject_options.py
django_datacite/migrations/0012_alter_geolocation_options.py
django_datacite/migrations/__init__.py
django_datacite/static/datacite/admin/css/datacite.css
django_datacite/templates/admin/datacite/resource/change_form.html
django_datacite/templates/admin/datacite/resource/change_list.html
django_datacite/templates/admin/datacite/resource/copy.html
django_datacite/templates/admin/datacite/resource/create_new_version.html
django_datacite/templates/admin/datacite/resource/import.html
django_datacite/templates/admin/datacite/resource/validate.html
django_datacite/templates/datacite/citation.html
django_datacite/templates/datacite/resource.bib
django_datacite/templates/datacite/resource.html
django_datacite/tests/test_admin.py
django_datacite/tests/test_import.py
django_datacite/tests/test_models.py
django_datacite/tests/test_views.py
django_datacite-1.1.1.dist-info/licenses/LICENSE
django_datacite-1.1.1.dist-info/METADATA
django_datacite-1.1.1.dist-info/WHEEL
django_datacite-1.1.1.dist-info/top_level.txt
django_datacite-1.1.1.dist-info/RECORD
