Metadata-Version: 2.4
Name: django-datacite
Version: 1.1.1
Summary: A Django app to properly model the DataCite Metadata Schema in a relational database,
Author-email: Jochen Klar <jochen.klar@pik-potsdam.de>
Maintainer-email: Jochen Klar <jochen.klar@pik-potsdam.de>
License: MIT License
Project-URL: Repository, https://github.com/ISI-MIP/django-datacite
Classifier: Operating System :: OS Independent
Classifier: License :: OSI Approved :: MIT License
Classifier: Programming Language :: Python :: 3.8
Classifier: Programming Language :: Python :: 3.9
Classifier: Programming Language :: Python :: 3.10
Classifier: Programming Language :: Python :: 3.11
Classifier: Programming Language :: Python :: 3.12
Classifier: Programming Language :: Python :: 3.13
Classifier: Programming Language :: Python :: 3.14
Requires-Python: >=3.8
License-File: LICENSE
Requires-Dist: datacite~=1.1.2
Requires-Dist: Django>=3.2.0
Requires-Dist: requests>=2.25.0
Provides-Extra: dev
Requires-Dist: build; extra == "dev"
Requires-Dist: pre-commit; extra == "dev"
Requires-Dist: ruff; extra == "dev"
Provides-Extra: pytest
Requires-Dist: dj_database_url~=2.0.0; extra == "pytest"
Requires-Dist: pytest~=7.4.0; extra == "pytest"
Requires-Dist: pytest-cov~=4.1.0; extra == "pytest"
Requires-Dist: pytest-django~=4.5.2; extra == "pytest"
Requires-Dist: pytest-dotenv~=0.5.2; extra == "pytest"
Requires-Dist: requests-mock~=1.11.0; extra == "pytest"
Dynamic: license-file
